bridgescaler/VERSION
bridgescaler/__init__.py
bridgescaler/backend.py
bridgescaler/deep.py
bridgescaler/distributed.py
bridgescaler/group.py
bridgescaler-0.7.1.dist-info/LICENSE
bridgescaler-0.7.1.dist-info/METADATA
bridgescaler-0.7.1.dist-info/WHEEL
bridgescaler-0.7.1.dist-info/top_level.txt
bridgescaler-0.7.1.dist-info/zip-safe
bridgescaler-0.7.1.dist-info/RECORD
