Metadata-Version: 2.1
Name: bridgescaler
Version: 0.7.1
Summary: Tool to automagically save scikit-learn scaler properties to a portable, readable format.
Home-page: https://github.com/NCAR/bridgescaler
Author: David John Gagne
Author-email: dgagne@ucar.edu
License: MIT
Keywords: machine learning
Platform: any
Classifier: Programming Language :: Python
Classifier: Programming Language :: Python :: 3.8
Classifier: Programming Language :: Python :: 3.9
Classifier: Programming Language :: Python :: 3.10
Classifier: Programming Language :: Python :: 3.11
Requires-Python: >=3.7
License-File: LICENSE
Requires-Dist: scikit-learn >=1.0
Requires-Dist: numpy
Requires-Dist: pandas
Requires-Dist: crick
Requires-Dist: scipy
Requires-Dist: xarray
Requires-Dist: numba
Requires-Dist: sphinx
Requires-Dist: sphinx-book-theme
